pmtiles/__init__.py
pmtiles/convert.py
pmtiles/reader.py
pmtiles/writer.py
pmtiles-0.2.0.data/scripts/mbtiles2pmtiles
pmtiles-0.2.0.data/scripts/pmtiles-convert
pmtiles-0.2.0.data/scripts/pmtiles-serve
pmtiles-0.2.0.data/scripts/pmtiles-show
pmtiles-0.2.0.dist-info/METADATA
pmtiles-0.2.0.dist-info/WHEEL
pmtiles-0.2.0.dist-info/top_level.txt
pmtiles-0.2.0.dist-info/RECORD
